interpret_community/__init__.py
interpret_community/tabular_explainer.py
interpret_community/version.py
interpret_community/_internal/__init__.py
interpret_community/_internal/raw_explain/__init__.py
interpret_community/_internal/raw_explain/data_mapper.py
interpret_community/_internal/raw_explain/data_mapper_utils.py
interpret_community/_internal/raw_explain/feature_mappers.py
interpret_community/_internal/raw_explain/raw_explain_utils.py
interpret_community/adapter/__init__.py
interpret_community/adapter/explanation_adapter.py
interpret_community/common/__init__.py
interpret_community/common/aggregate.py
interpret_community/common/base_explainer.py
interpret_community/common/blackbox_explainer.py
interpret_community/common/chained_identity.py
interpret_community/common/constants.py
interpret_community/common/error_handling.py
interpret_community/common/exception.py
interpret_community/common/explanation_utils.py
interpret_community/common/gpu_kmeans.py
interpret_community/common/metrics.py
interpret_community/common/model_summary.py
interpret_community/common/policy.py
interpret_community/common/progress.py
interpret_community/common/serialization_utils.py
interpret_community/common/structured_model_explainer.py
interpret_community/common/warnings_suppressor.py
interpret_community/common/model_wrapper/__init__.py
interpret_community/dataset/__init__.py
interpret_community/dataset/decorator.py
interpret_community/dataset/dataset_wrapper/__init__.py
interpret_community/explanation/__init__.py
interpret_community/explanation/explanation.py
interpret_community/explanation/serialization.py
interpret_community/lime/__init__.py
interpret_community/lime/lime_explainer.py
interpret_community/mimic/__init__.py
interpret_community/mimic/mimic_explainer.py
interpret_community/mimic/model_distill.py
interpret_community/mimic/models/__init__.py
interpret_community/mimic/models/explainable_model.py
interpret_community/mimic/models/lightgbm_model.py
interpret_community-0.31.0.dist-info/LICENSE.txt
interpret_community-0.31.0.dist-info/METADATA
interpret_community-0.31.0.dist-info/WHEEL
interpret_community-0.31.0.dist-info/entry_points.txt
interpret_community-0.31.0.dist-info/top_level.txt
interpret_community-0.31.0.dist-info/RECORD
