Metadata-Version: 2.1
Name: interpret_community
Version: 0.31.0
Summary: Microsoft Interpret Extensions SDK for Python
Home-page: https://github.com/interpretml/interpret-community
Author: Microsoft Corp
Author-email: ilmat@microsoft.com
License: MIT License
Classifier: Development Status :: 5 - Production/Stable
Classifier: Intended Audience :: Developers
Classifier: Intended Audience :: Science/Research
Classifier: License :: OSI Approved :: MIT License
Classifier: Programming Language :: Python :: 3
Classifier: Programming Language :: Python :: 3.7
Classifier: Programming Language :: Python :: 3.8
Classifier: Programming Language :: Python :: 3.9
Classifier: Topic :: Scientific/Engineering :: Artificial Intelligence
Classifier: Operating System :: Microsoft :: Windows
Classifier: Operating System :: MacOS
Classifier: Operating System :: POSIX :: Linux
License-File: LICENSE.txt
Requires-Dist: numpy
Requires-Dist: pandas <2.0.0
Requires-Dist: scipy
Requires-Dist: ml-wrappers ~=0.5.4
Requires-Dist: scikit-learn
Requires-Dist: packaging
Requires-Dist: shap <=0.44.0,>=0.20.0
Requires-Dist: raiutils ~=0.4.0
Requires-Dist: interpret-core <0.5.0,>=0.1.20 ; python_version <= "3.7"
Requires-Dist: interpret-core <=0.5.0,>=0.1.20 ; python_version >= "3.8"
Provides-Extra: deep
Requires-Dist: tensorflow ; extra == 'deep'
Requires-Dist: pyyaml ; extra == 'deep'
Requires-Dist: keras ; extra == 'deep'
Provides-Extra: lime
Requires-Dist: lime >=0.2.0.0 ; extra == 'lime'
Provides-Extra: mimic
Requires-Dist: lightgbm ; extra == 'mimic'
Provides-Extra: sample
Requires-Dist: hdbscan ; extra == 'sample'
